pix_utils/Base.py
pix_utils/CNPJ.py
pix_utils/CPF.py
pix_utils/Email.py
pix_utils/Phone.py
pix_utils/Pix.py
pix_utils/Random.py
pix_utils/Type.py
pix_utils/__init__.py
pix_utils-1.0.0.dist-info/LICENSE
pix_utils-1.0.0.dist-info/METADATA
pix_utils-1.0.0.dist-info/WHEEL
pix_utils-1.0.0.dist-info/top_level.txt
pix_utils-1.0.0.dist-info/RECORD
