Metadata-Version: 2.1
Name: pix-utils
Version: 1.0.0
Summary: A module for useful functions related to the Brazilian payment system PIX.
Home-page: https://github.com/alvarofpp/validate-docbr
Author: Gustavo Santana
Author-email: sowlfie@gmail.com
Classifier: Programming Language :: Python :: 3
Classifier: License :: OSI Approved :: MIT License
Classifier: Operating System :: OS Independent
License-File: LICENSE
